[
    {
        "Offer": "48% OFF",
        "Company Name": "Wonderchef",
        "Product Details": "Wonderchef\nNutri-Cup Portable Blender USB Charging - Smoothie Maker, SS Blades, Rechargeable Blender, Blue\n300 ml",
        "Pack Details": "300 ml",
        "Discounted Price": "₹1299",
        "Original Price": "₹2500"
    },
    {
        "Offer": "52% OFF",
        "Company Name": "Prestige",
        "Product Details": "Prestige\nElectric Kettle PKOSS 1.5, 1500 W - Silver, Black, Automatic Cut Off, Stainless Steel\n1.5 L",
        "Pack Details": "1.5 L",
        "Discounted Price": "₹699",
        "Original Price": "₹1445"
    },
    {
        "Offer": "16% OFF",
        "Company Name": "Duracell",
        "Product Details": "Duracell\nUltra Alkaline AA Batteries\n4 pcs",
        "Pack Details": "No Pack Details",
        "Discounted Price": "₹160",
        "Original Price": "₹190"
    },
    {
        "Offer": "32% OFF",
        "Company Name": "Eveready",
        "Product Details": "Eveready\nUltima Alkaline AA Battery - 400% Longer Lasting\n4.1\n8 Ratings\n10 pcs",
        "Pack Details": "10 pcs",
        "Discounted Price": "₹149",
        "Original Price": "₹220"
    },
    {
        "Offer": "32% OFF",
        "Company Name": "Prestige",
        "Product Details": "Prestige\nPEG 6.0 1000W Electric Griller, Aluminium Non-Stick Plates, Heat Resistant Exterior, Low Fat Grilling\n1.7\n3 Ratings\n1 pc",
        "Pack Details": "1 pc",
        "Discounted Price": "₹1899",
        "Original Price": "₹2795"
    },
    {
        "Offer": "17% OFF",
        "Company Name": "Eveready",
        "Product Details": "Eveready\nCarbon Zinc AA Battery\n2 x 10 pcs - (Multipack)",
        "Pack Details": "No Pack Details",
        "Discounted Price": "₹300.51",
        "Original Price": "₹360"
    },
    {
        "Offer": "₹34 OFF",
        "Company Name": "Anchor by Panasonic",
        "Product Details": "Anchor by Panasonic\n3 Socket Extension Board - Plastic, 5208, 4 mtr, 6 Amps\n1 pc",
        "Pack Details": "1 pc",
        "Discounted Price": "₹319",
        "Original Price": "₹353"
    },
    {
        "Offer": "59% OFF",
        "Company Name": "SBE",
        "Product Details": "SBE\nElectric Diya\n1 pc",
        "Pack Details": "1 pc",
        "Discounted Price": "₹99",
        "Original Price": "₹240"
    },
    {
        "Offer": "90% OFF",
        "Company Name": "Desidiya",
        "Product Details": "Desidiya\nLED Rice Light For Decoration String & Series Light 12 Metre 39.37 Feet, Multi\n1 pc",
        "Pack Details": "1 pc",
        "Discounted Price": "₹99",
        "Original Price": "₹999"
    },
    {
        "Offer": "36% OFF",
        "Company Name": "MANSAA",
        "Product Details": "MANSAA\n300 LED Curtain Light - 8 Lighting Modes, USB Operated, Warm White, 3 M X 3 M\n1 pc",
        "Pack Details": "1 pc",
        "Discounted Price": "₹699",
        "Original Price": "₹1099"
    },
    {
        "Offer": "32% OFF",
        "Company Name": "Eveready",
        "Product Details": "Eveready\nUltima Alkaline AAA Battery - 400% Longer Lasting\n3.7\n10 Ratings\n10 pcs",
        "Pack Details": "10 pcs",
        "Discounted Price": "₹149",
        "Original Price": "₹220"
    },
    {
        "Offer": "60% OFF",
        "Company Name": "Desidiya",
        "Product Details": "Desidiya\nPixel Rice Light - 40 Ft, Warm White/Yellow, Energy Efficient, For Home Decor\n1 pc",
        "Pack Details": "1 pc",
        "Discounted Price": "₹119",
        "Original Price": "₹299"
    },
    {
        "Offer": "54% OFF",
        "Company Name": "Desidiya",
        "Product Details": "Desidiya\nFlameless LED Tea Light Candles - Mood Light\n6 pcs",
        "Pack Details": "6 pcs",
        "Discounted Price": "₹229",
        "Original Price": "₹499"
    },
    {
        "Offer": "93% OFF",
        "Company Name": "Desidiya",
        "Product Details": "Desidiya\nDecorative Pixel Rice Light 22 m Warm - White\n1 pc",
        "Pack Details": "1 pc",
        "Discounted Price": "₹149",
        "Original Price": "₹1999"
    },
    {
        "Offer": "75% OFF",
        "Company Name": "MANSAA",
        "Product Details": "MANSAA\nUSB Copper String Fairy Lights - 3 M, 30 LED, Multicolour, For Home Decor\n1 pc",
        "Pack Details": "1 pc",
        "Discounted Price": "₹99",
        "Original Price": "₹399"
    },
    {
        "Offer": "40% OFF",
        "Company Name": "MANSAA",
        "Product Details": "MANSAA\nDiya Curtain String Lights - 108 LEDs With Flashing Modes, 2.5 m, For Home Decor, Warm White\n1 pc",
        "Pack Details": "1 pc",
        "Discounted Price": "₹599",
        "Original Price": "₹999"
    },
    {
        "Offer": "37% OFF",
        "Company Name": "Lifelong",
        "Product Details": "Lifelong\nRegalia Plus 1200 W Halogen Room Heater - LLHH921\n1 pc",
        "Pack Details": "1 pc",
        "Discounted Price": "₹1899",
        "Original Price": "₹3000"
    },
    {
        "Offer": "33% OFF",
        "Company Name": "Prestige",
        "Product Details": "Prestige\nExpress PEX 3.0 Mixer Grinder - With Multipurpose Jars Of 500 ml & 300 ml, Silver\n1 pc",
        "Pack Details": "1 pc",
        "Discounted Price": "₹2299",
        "Original Price": "₹3445"
    },
    {
        "Offer": "₹21 OFF",
        "Company Name": "Eveready",
        "Product Details": "Eveready\nUltima Pro Alkaline AAA Battery 1.5 Volt, 800% Long Lasting\n2.7\n3 Ratings\n6 pcs",
        "Pack Details": "6 pcs",
        "Discounted Price": "₹249",
        "Original Price": "₹270"
    },
    {
        "Offer": "69% OFF",
        "Company Name": "Eveready",
        "Product Details": "Eveready\nCopper String Light 6500K\n2.8\n11 Ratings\n1 pc",
        "Pack Details": "1 pc",
        "Discounted Price": "₹199",
        "Original Price": "₹649"
    },
    {
        "Offer": "34% OFF",
        "Company Name": "Philips",
        "Product Details": "Philips\nLED T-Bulb - 18 Watt, Cool Daylight, B22\n3.9\n155 Ratings\n1 pc",
        "Pack Details": "1 pc",
        "Discounted Price": "₹329",
        "Original Price": "₹500"
    },
    {
        "Offer": "31% OFF",
        "Company Name": "Philips",
        "Product Details": "Philips\nStarlit 72 LEDs String Light - 12 Mtr, Bright, Warm White, For Home Decor\n4\n20 Ratings\n1 pc",
        "Pack Details": "1 pc",
        "Discounted Price": "₹249",
        "Original Price": "₹360"
    },
    {
        "Offer": "43% OFF",
        "Company Name": "bb home",
        "Product Details": "bb home\nAlkaline AAA Batteries\n3.7\n32 Ratings\n4 pcs",
        "Pack Details": "No Pack Details",
        "Discounted Price": "₹69",
        "Original Price": "₹120"
    },
    {
        "Offer": "20% OFF",
        "Company Name": "Beardo",
        "Product Details": "Beardo\nApe-X 3-in-1 Trimmer,Nose Trimmer, Shaver, Manscaping,120 minute run time,Engineered for Men\n3.5\n15 Ratings\n120 g",
        "Pack Details": "120 g",
        "Discounted Price": "₹1199",
        "Original Price": "₹1499"
    },
    {
        "Offer": "80% OFF",
        "Company Name": "Desidiya",
        "Product Details": "Desidiya\nLED Star Shaped String Lights Energy Efficient - For Home Decor\n1 pc",
        "Pack Details": "1 pc",
        "Discounted Price": "₹399",
        "Original Price": "₹1999"
    },
    {
        "Offer": "33% OFF",
        "Company Name": "Prestige",
        "Product Details": "Prestige\nXpress 1200W Induction Cooktop - With Ceramic Plates, Black\n1 pc",
        "Pack Details": "1 pc",
        "Discounted Price": "₹1799",
        "Original Price": "₹2695"
    },
    {
        "Offer": "56% OFF",
        "Company Name": "Duracell",
        "Product Details": "Duracell\nType A To Lightning Mfi Braided Cable - 1.2 m, For Apple Devices, Black\n5\n2 Ratings\n1 pc",
        "Pack Details": "1 pc",
        "Discounted Price": "₹799",
        "Original Price": "₹1799"
    },
    {
        "Offer": "46% OFF",
        "Company Name": "Energizer",
        "Product Details": "Energizer\nAlkaline Power Battery - AA, 1.5 V, Mercury-Free\n4\n136 Ratings\n4 pcs - Blister Pack",
        "Pack Details": "4 pcs - Blister Pack",
        "Discounted Price": "₹109",
        "Original Price": "₹200"
    },
    {
        "Offer": "64% OFF",
        "Company Name": "Lifelong",
        "Product Details": "Lifelong\nPower Pro Mixer Grinder - Black, 500 W\n1 pc - (3 Jars - 1.5 L, 0.3 L, 0.8 L)",
        "Pack Details": "1 pc - (3 Jars - 1.5 L, 0.3 L, 0.8 L)",
        "Discounted Price": "₹1249",
        "Original Price": "₹3500"
    },
    {
        "Offer": "12% OFF",
        "Company Name": "Eveready",
        "Product Details": "Eveready\nCarbon Zinc AAA Battery\n4\n48 Ratings\n12 pcs",
        "Pack Details": "12 pcs",
        "Discounted Price": "₹190",
        "Original Price": "₹216"
    },
    {
        "Offer": "63% OFF",
        "Company Name": "Zebronics",
        "Product Details": "Zebronics\nZeb-Bro Ear Wired Earphones - With Mic, 3.5mm Audio Jack, Phone/Tablet Compatible, Blue\n1 pc",
        "Pack Details": "1 pc",
        "Discounted Price": "₹149",
        "Original Price": "₹399"
    },
    {
        "Offer": "67% OFF",
        "Company Name": "Lifelong",
        "Product Details": "Lifelong\nUSB Rechargeable Wireless Electric Chopper - With Stainless Steel Blades, Pink, LLWC03\n250 ml",
        "Pack Details": "250 ml",
        "Discounted Price": "₹499",
        "Original Price": "₹1500"
    },
    {
        "Offer": "67% OFF",
        "Company Name": "boAt",
        "Product Details": "boAt\nStone 650 Bluetooth Speaker - Charcoal Black\n1 pc",
        "Pack Details": "1 pc",
        "Discounted Price": "₹1649",
        "Original Price": "₹4990"
    },
    {
        "Offer": "80% OFF",
        "Company Name": "Lexton",
        "Product Details": "Lexton\n40 LED Power Pixel Serial String/Fairy Light - 36 Ft Long, Plug Sourced, Multicolour\n1 pc",
        "Pack Details": "1 pc",
        "Discounted Price": "₹99",
        "Original Price": "₹499"
    },
    {
        "Offer": "56% OFF",
        "Company Name": "Pigeon by Stovekraft",
        "Product Details": "Pigeon by Stovekraft\nCruise Induction Cooktop - With Crystal Glass, 1800 Watt, 7 Segments LED Display, Auto Switch Off\n1 pc",
        "Pack Details": "1 pc",
        "Discounted Price": "₹1399",
        "Original Price": "₹3195"
    },
    {
        "Offer": "25% OFF",
        "Company Name": "Eveready",
        "Product Details": "Eveready\nCarbon Zinc Battery Red AAA 1012\n2 x 4 pcs - Multipack",
        "Pack Details": "No Pack Details",
        "Discounted Price": "₹98.07",
        "Original Price": "₹130"
    },
    {
        "Offer": "68% OFF",
        "Company Name": "Desidiya",
        "Product Details": "Desidiya\nStar Window String Lights Energy Efficient - For Home Decor, Corded\n1 pc",
        "Pack Details": "1 pc",
        "Discounted Price": "₹649",
        "Original Price": "₹1999"
    },
    {
        "Offer": "63% OFF",
        "Company Name": "Wonderchef",
        "Product Details": "Wonderchef\nCrescent Electric Kettle,Used For Boiling Water, Making Tea & Coffee, Instant Noodles, Soup\n3.2\n59 Ratings\n1.5 L",
        "Pack Details": "1.5 L",
        "Discounted Price": "₹599",
        "Original Price": "₹1600"
    },
    {
        "Offer": "21% OFF",
        "Company Name": "Eveready",
        "Product Details": "Eveready\n2.5 W LED Light Bulb Cool Day Light, 6500K, With Wide Operating Voltage Range\n4.4\n106 Ratings\n1 pc",
        "Pack Details": "1 pc",
        "Discounted Price": "₹79",
        "Original Price": "₹100"
    },
    {
        "Offer": "52% OFF",
        "Company Name": "Wonderchef",
        "Product Details": "Wonderchef\nOnyx Brew Coffee Maker - Borosilicate Glass Carafe, Anti-Drip System\n3\n3 Ratings\n1 pc",
        "Pack Details": "1 pc",
        "Discounted Price": "₹1349",
        "Original Price": "₹2800"
    },
    {
        "Offer": "50% OFF",
        "Company Name": "Lifelong",
        "Product Details": "Lifelong\nPower Pro 500-Watt Mixer Grinder - With 3 Jars, Liquidizing, Wet Grinding & Chutney Jar, Stainless Steel Blades, 1 Year Warranty, White/Grey, LLMG45\n1 pc",
        "Pack Details": "1 pc",
        "Discounted Price": "₹1249",
        "Original Price": "₹2499"
    },
    {
        "Offer": "12% OFF",
        "Company Name": "Duracell",
        "Product Details": "Duracell\nChhota Power Alkaline Battery - AA, 1.5 V, Leak-Proof\n2 x 10 pcs - (Multipack)",
        "Pack Details": "No Pack Details",
        "Discounted Price": "₹388.05",
        "Original Price": "₹440"
    },
    {
        "Offer": "14% OFF",
        "Company Name": "Duracell",
        "Product Details": "Duracell\nUltra Alkaline AAA Batteries\n6 pcs",
        "Pack Details": "No Pack Details",
        "Discounted Price": "₹259",
        "Original Price": "₹300"
    },
    {
        "Offer": "19% OFF",
        "Company Name": "Havells",
        "Product Details": "Havells\nBT5301 Zoom Wheel Fast Charge Trimmer\n1 pc",
        "Pack Details": "1 pc",
        "Discounted Price": "₹1620.94",
        "Original Price": "₹1995"
    },
    {
        "Offer": "91% OFF",
        "Company Name": "Nu Republic",
        "Product Details": "Nu Republic\nType C To Type C Blaze Supersonic 65W Fast Charging Cable - 1 m, Red\n3\n3 Ratings\n1 pc",
        "Pack Details": "1 pc",
        "Discounted Price": "₹115",
        "Original Price": "₹1299"
    },
    {
        "Offer": "55% OFF",
        "Company Name": "Wonderchef",
        "Product Details": "Wonderchef\nPrato Plus Griller - Auto Temp Control, LED indicator, 800 W\n3.3\n4 Ratings\n1 pc",
        "Pack Details": "1 pc",
        "Discounted Price": "₹999",
        "Original Price": "₹2200"
    },
    {
        "Offer": "79% OFF",
        "Company Name": "Lexton",
        "Product Details": "Lexton\n20 LED Star String Lights - 3 M, Plug Sourced, Warm White\n1 pc",
        "Pack Details": "1 pc",
        "Discounted Price": "₹149",
        "Original Price": "₹699"
    },
    {
        "Offer": "79% OFF",
        "Company Name": "Lexton",
        "Product Details": "Lexton\n16 LED Blossom Flower Fairy/String Lights - Plug Sourced, Warm White\n1 pc",
        "Pack Details": "1 pc",
        "Discounted Price": "₹149",
        "Original Price": "₹699"
    }
]